pytmp3/__init__.py
pytmp3/__main__.py
pytmp3-0.0.7.dist-info/LICENCE.md
pytmp3-0.0.7.dist-info/METADATA
pytmp3-0.0.7.dist-info/WHEEL
pytmp3-0.0.7.dist-info/top_level.txt
pytmp3-0.0.7.dist-info/RECORD
