Metadata-Version: 2.1
Name: pytmp3
Version: 0.0.7
Summary: Easily download albums, playlists and songs off YouTube to MP3 format
Author: Spacerulerwill (William Redding)
Author-email: <williamdredding@gmail.com>
Keywords: python,youtube,mp3,music,utility,tool
Classifier: Intended Audience :: End Users/Desktop
Classifier: Programming Language :: Python :: 3
Classifier: Operating System :: Unix
Classifier: Operating System :: MacOS :: MacOS X
Classifier: Operating System :: Microsoft :: Windows
License-File: LICENCE.md
Requires-Dist: youtube-search-python
Requires-Dist: pytube
Requires-Dist: alive-progress
Requires-Dist: mutagen
Requires-Dist: requests
Requires-Dist: black
